mlars/__init__.py
mlars/getData.py
mlars/models.py
mlars-0.0.4.dist-info/METADATA
mlars-0.0.4.dist-info/WHEEL
mlars-0.0.4.dist-info/top_level.txt
mlars-0.0.4.dist-info/RECORD
