Metadata-Version: 2.1
Name: mlars
Version: 0.0.4
Summary: a library for recommending ml algorithms
Author: prashantm2001 , HaiderNakara
Author-email: <prashant.om@somaiya.edu>,<haider.n@somaiya.edu>
License: UNKNOWN
Keywords: python,video,machine-learning,recommendation
Platform: UNKNOWN
Classifier: Development Status :: 1 - Planning
Classifier: Intended Audience :: Developers
Classifier: Programming Language :: Python :: 3
Classifier: Operating System :: Unix
Classifier: Operating System :: MacOS :: MacOS X
Classifier: Operating System :: Microsoft :: Windows
Requires-Dist: colorama
Requires-Dist: numpy
Requires-Dist: pandas
Requires-Dist: scikit-learn
